<edmx:Edmx xmlns:edmx="http://docs.oasis-open.org/odata/ns/edmx" Version="4.0">
	<edmx:Reference Uri="/sap/bc/ui5_ui5/ui2/ushell/resources/sap/ushell/components/factsheet/vocabularies/UI.xml">
		<edmx:Include Alias="UI" Namespace="com.sap.vocabularies.UI.v1"/>
	</edmx:Reference>
	<edmx:Reference Uri="/sap/bc/ui5_ui5/ui2/ushell/resources/sap/ushell/components/factsheet/vocabularies/Communication.xml">
		<edmx:Include Alias="vCard" Namespace="com.sap.vocabularies.Communication.v1"/>
	</edmx:Reference>
	<edmx:Reference Uri="/sap/bc/ui5_ui5/ui2/ushell/resources/sap/ushell/components/factsheet/vocabularies/Common.xml">
		<edmx:Include Alias="Common" Namespace="com.sap.vocabularies.Common.v1"/>
	</edmx:Reference>
	<edmx:Reference Uri="http://docs.oasis-open.org/odata/odata/v4.0/errata02/os/complete/vocabularies/Org.OData.Core.V1.xml">
		<edmx:Include Alias="Core" Namespace="Org.OData.Core.V1"/>
	</edmx:Reference>
	<edmx:Reference Uri="http://docs.oasis-open.org/odata/odata/v4.0/cs01/vocabularies/Org.OData.Measures.V1.xml">
		<edmx:Include Alias="CQP" Namespace="Org.OData.Measures.V1"/>
	</edmx:Reference>
	<edmx:Reference Uri="http://docs.oasis-open.org/odata/odata/v4.0/cs01/vocabularies/Org.OData.Capabilities.V1.xml">
		<edmx:Include Alias="Capabilities" Namespace="Org.OData.Capabilities.V1"/>
	</edmx:Reference>
	<edmx:Reference Uri="http://docs.oasis-open.org/odata/odata-data-aggregation-ext/v4.0/cs02/vocabularies/Org.OData.Aggregation.V1.xml">
		<edmx:Include Alias="Aggregation" Namespace="Org.OData.Aggregation.V1"/>
	</edmx:Reference>
	<edmx:DataServices>
		<Schema xmlns="http://docs.oasis-open.org/odata/ns/edm">
			<Annotations Target="/EVORA/EL_NOTIFICATION_SRV.PMNotification/Maintobjectdowntimeduration">
				<Annotation Term="CQP.Unit"/>
			</Annotations>
			<Annotations Target="/EVORA/EL_NOTIFICATION_SRV.PMNotification">
				<Annotation Term="UI.HeaderInfo">
					<Record Type="UI.HeaderInfoType">
						<PropertyValue Property="TypeName" String="{@i18n&gt;@MAINTENANCE_NOTIFICATION}"/>
						<PropertyValue Property="TypeNamePlural" String="{@i18n&gt;@MAINTENANCE_NOTIFICATIONS}"/>
						<PropertyValue Property="Title">
							<Record Type="UI.DataField">
								<PropertyValue Property="Value" Path="Maintenancenotification"/>
							</Record>
						</PropertyValue>
						<PropertyValue Property="Description">
							<Record Type="UI.DataField">
								<PropertyValue Property="Value" Path="Notificationtext"/>
							</Record>
						</PropertyValue>
					</Record>
				</Annotation>
				<Annotation Term="UI.SelectionFields">
					<Collection>
						<PropertyPath>Maintenancenotification</PropertyPath>
						<PropertyPath>Notificationtype</PropertyPath>
						<PropertyPath>Requiredstartdate</PropertyPath>
						<PropertyPath>Requiredenddate</PropertyPath>
						<PropertyPath>Creationdate</PropertyPath>
						<PropertyPath>Notifprocessingphase</PropertyPath>
						<PropertyPath>Createdbyuser</PropertyPath>
						<PropertyPath>Maintpriority</PropertyPath>
						<PropertyPath>Maintenanceobjectisdown</PropertyPath>
					</Collection>
				</Annotation>
				<Annotation Term="UI.FieldGroup" Qualifier="Malfunction1">
					<Record Type="UI.FieldGroupType">
						<PropertyValue Property="Label" String="{@i18n&gt;@MALFUNCTION_START_DATE_AND_TIME}"/>
						<PropertyValue Property="Data">
							<Collection>
								<Record Type="UI.DataField">
									<PropertyValue Property="Value" Path="Malfunctionstartdate"/>
								</Record>
								<Record Type="UI.DataField">
									<PropertyValue Property="Label" String="{@i18n&gt;@MALFUNCTION_STARTED_AT}"/>
									<PropertyValue Property="Value" Path="Malfunctionstarttime"/>
								</Record>
							</Collection>
						</PropertyValue>
					</Record>
				</Annotation>
				<Annotation Term="UI.FieldGroup" Qualifier="Malfunction2">
					<Record Type="UI.FieldGroupType">
						<PropertyValue Property="Label" String="{@i18n&gt;@MALFUNCTION_END_DATE_AND_TIME}"/>
						<PropertyValue Property="Data">
							<Collection>
								<Record Type="UI.DataField">
									<PropertyValue Property="Value" Path="Malfunctionenddate"/>
								</Record>
								<Record Type="UI.DataField">
									<PropertyValue Property="Label" String="{@i18n&gt;@MALFUNCTION_ENDED_AT}"/>
									<PropertyValue Property="Value" Path="Malfunctionendtime"/>
								</Record>
							</Collection>
						</PropertyValue>
					</Record>
				</Annotation>
				<Annotation Term="UI.FieldGroup" Qualifier="Malfunction3">
					<Record Type="UI.FieldGroupType">
						<PropertyValue Property="Data">
							<Collection>
								<Record Type="UI.DataField">
									<PropertyValue Property="Value" Path="Maintobjectdowntimeduration"/>
								</Record>
								<Record Type="UI.DataField">
									<PropertyValue Property="Value" Path="Maintenanceobjectisdown"/>
									<Annotation Term="UI.Importance" EnumMember="UI.ImportanceType/High"/>
								</Record>
							</Collection>
						</PropertyValue>
					</Record>
				</Annotation>
				<Annotation Term="UI.FieldGroup" Qualifier="Dates">
					<Record Type="UI.FieldGroupType">
						<PropertyValue Property="Label" String="{@i18n&gt;@DATES}"/>
						<PropertyValue Property="Data">
							<Collection>
								<Record Type="UI.DataField">
									<PropertyValue Property="Value" Path="Requiredstartdate"/>
								</Record>
								<Record Type="UI.DataField">
									<PropertyValue Property="Label" String="{@i18n&gt;@REQUIRED_START_TIME}"/>
									<PropertyValue Property="Value" Path="Requiredstarttime"/>
								</Record>
								<Record Type="UI.DataField">
									<PropertyValue Property="Value" Path="Requiredenddate"/>
								</Record>
								<Record Type="UI.DataField">
									<PropertyValue Property="Label" String="{@i18n&gt;@REQUIRED_END_TIME}"/>
									<PropertyValue Property="Value" Path="Requiredendtime"/>
								</Record>
								<Record Type="UI.DataField">
									<PropertyValue Property="Value" Path="Maintenancerevision"/>
								</Record>
							</Collection>
						</PropertyValue>
					</Record>
				</Annotation>
				<Annotation Term="UI.FieldGroup" Qualifier="Location">
					<Record Type="UI.FieldGroupType">
						<PropertyValue Property="Label" String="{@i18n&gt;@LOCATION_DATA}"/>
						<PropertyValue Property="Data">
							<Collection>
								<Record Type="UI.DataField">
									<PropertyValue Property="Value" Path="Maintenanceworkcenterplant"/>
								</Record>
								<Record Type="UI.DataField">
									<PropertyValue Property="Value" Path="Assetlocation"/>
								</Record>
								<Record Type="UI.DataField">
									<PropertyValue Property="Value" Path="Maintenanceplant"/>
								</Record>
							</Collection>
						</PropertyValue>
					</Record>
				</Annotation>
				<Annotation Term="UI.FieldGroup" Qualifier="General">
					<Record Type="UI.FieldGroupType">
						<PropertyValue Property="Label" String="{@i18n&gt;@GENERAL}"/>
						<PropertyValue Property="Data">
							<Collection>
								<Record Type="UI.DataField">
									<PropertyValue Property="Value" Path="Notificationtype"/>
								</Record>
								<Record Type="UI.DataField">
									<PropertyValue Property="Value" Path="Creationdate"/>
								</Record>
								<Record Type="UI.DataField">
									<PropertyValue Property="Value" Path="Creationtime"/>
								</Record>
								<Record Type="UI.DataField">
									<PropertyValue Property="Value" Path="Maintpriority"/>
									<Annotation Term="UI.Importance" EnumMember="UI.ImportanceType/High"/>
								</Record>
								<Record Type="UI.DataField">
									<PropertyValue Property="Value" Path="Reportedbyuser"/>
								</Record>
								<Record Type="UI.DataField">
									<PropertyValue Property="Value" Path="Createdbyuser"/>
								</Record>
							</Collection>
						</PropertyValue>
					</Record>
				</Annotation>
				<Annotation Term="UI.FieldGroup" Qualifier="HeaderGeneral">
					<Record Type="UI.FieldGroupType">
						<PropertyValue Property="Label" String="{@i18n&gt;@PRIORITY}"/>
						<PropertyValue Property="Data">
							<Collection>
								<Record Type="UI.DataField">
									<PropertyValue Property="Value" Path="Notificationtype"/>
								</Record>
								<Record Type="UI.DataField">
									<PropertyValue Property="Value" Path="Maintpriority"/>
									<Annotation Term="UI.Importance" EnumMember="UI.ImportanceType/High"/>
								</Record>
								<Record Type="UI.DataField">
									<PropertyValue Property="Value" Path="Maintenanceobjectisdown"/>
									<Annotation Term="UI.Importance" EnumMember="UI.ImportanceType/High"/>
								</Record>
							</Collection>
						</PropertyValue>
					</Record>
				</Annotation>
				<Annotation Term="UI.LineItem">
					<Collection>
						<Record Type="UI.DataField">
							<Annotation Term="UI.Importance" EnumMember="UI.ImportanceType/High"/>
							<PropertyValue Property="Value" Path="Maintenancenotification"/>
						</Record>
						<Record Type="UI.DataField">
							<Annotation Term="UI.Importance" EnumMember="UI.ImportanceType/High"/>
							<PropertyValue Property="Value" Path="Notificationtext"/>
						</Record>
						<Record Type="UI.DataField">
							<PropertyValue Property="Value" Path="Notificationtypename"/>
							<Annotation Term="UI.Importance" EnumMember="UI.ImportanceType/High"/>
						</Record>
						<Record Type="UI.DataField">
							<PropertyValue Property="Value" Path="Requiredstartdate"/>
							<Annotation Term="UI.Importance" EnumMember="UI.ImportanceType/High"/>
						</Record>
						<Record Type="UI.DataField">
							<PropertyValue Property="Value" Path="Requiredenddate"/>
							<Annotation Term="UI.Importance" EnumMember="UI.ImportanceType/High"/>
						</Record>
						<Record Type="UI.DataField">
							<Annotation Term="UI.Importance" EnumMember="UI.ImportanceType/High"/>
							<PropertyValue Property="Value" Path="Creationdate"/>
						</Record>
						<Record Type="UI.DataField">
							<Annotation Term="UI.Importance" EnumMember="UI.ImportanceType/High"/>
							<PropertyValue Property="Value" Path="Notifprocessingphase"/>
						</Record>
						<Record Type="UI.DataField">
							<PropertyValue Property="Value" Path="Createdbyuser"/>
							<Annotation Term="UI.Importance" EnumMember="UI.ImportanceType/High"/>
						</Record>
					</Collection>
				</Annotation>
			</Annotations>
		</Schema>
	</edmx:DataServices>
</edmx:Edmx>